aiovertica/__init__.py
aiovertica/column.py
aiovertica/compat.py
aiovertica/connection.py
aiovertica/cursor.py
aiovertica/datatypes.py
aiovertica/errors.py
aiovertica/log.py
aiovertica/messages/__init__.py
aiovertica/messages/backend_messages/__init__.py
aiovertica/messages/backend_messages/authentication.py
aiovertica/messages/backend_messages/backend_key_data.py
aiovertica/messages/backend_messages/bind_complete.py
aiovertica/messages/backend_messages/close_complete.py
aiovertica/messages/backend_messages/command_complete.py
aiovertica/messages/backend_messages/command_description.py
aiovertica/messages/backend_messages/copy_done_response.py
aiovertica/messages/backend_messages/copy_in_response.py
aiovertica/messages/backend_messages/data_row.py
aiovertica/messages/backend_messages/empty_query_response.py
aiovertica/messages/backend_messages/end_of_batch_response.py
aiovertica/messages/backend_messages/error_response.py
aiovertica/messages/backend_messages/load_balance_response.py
aiovertica/messages/backend_messages/load_file.py
aiovertica/messages/backend_messages/no_data.py
aiovertica/messages/backend_messages/notice_response.py
aiovertica/messages/backend_messages/parameter_description.py
aiovertica/messages/backend_messages/parameter_status.py
aiovertica/messages/backend_messages/parse_complete.py
aiovertica/messages/backend_messages/portal_suspended.py
aiovertica/messages/backend_messages/ready_for_query.py
aiovertica/messages/backend_messages/row_description.py
aiovertica/messages/backend_messages/unknown.py
aiovertica/messages/backend_messages/verify_files.py
aiovertica/messages/backend_messages/write_file.py
aiovertica/messages/frontend_messages/__init__.py
aiovertica/messages/frontend_messages/bind.py
aiovertica/messages/frontend_messages/cancel_request.py
aiovertica/messages/frontend_messages/close.py
aiovertica/messages/frontend_messages/copy_data.py
aiovertica/messages/frontend_messages/copy_done.py
aiovertica/messages/frontend_messages/copy_error.py
aiovertica-0.0.5.dist-info/LICENSE
aiovertica-0.0.5.dist-info/WHEEL
aiovertica-0.0.5.dist-info/METADATA
aiovertica-0.0.5.dist-info/RECORD
