Metadata-Version: 2.1
Name: aiovertica
Version: 0.0.5
Summary: Small asynchronous driver for Vertica based on vertica_python
Home-page: https://github.com/i8enn/aiovertica
License: Apache-2.0
Author: Ivan Galin
Author-email: i.galin@devartsteam.ru
Requires-Python: >=3.8,<3.10
Classifier: Development Status :: 1 - Planning
Classifier: Intended Audience :: Developers
Classifier: License :: OSI Approved :: Apache Software License
Classifier: Operating System :: OS Independent
Classifier: Programming Language :: Python
Classifier: Programming Language :: Python :: 3
Classifier: Programming Language :: Python :: 3.8
Classifier: Programming Language :: Python :: 3.9
Classifier: Topic :: Database
Classifier: Topic :: Database :: Database Engines/Servers
Classifier: Topic :: Database :: Front-Ends
Classifier: Topic :: Software Development :: Libraries :: Python Modules
Requires-Dist: python-dateutil (>=2.8.2,<3.0.0)
Requires-Dist: six (>=1.16.0,<2.0.0)
